fastlimiter/__init__.py
fastlimiter/fastlimiter.py
fastlimiter-0.1.0.dist-info/LICENSE
fastlimiter-0.1.0.dist-info/METADATA
fastlimiter-0.1.0.dist-info/WHEEL
fastlimiter-0.1.0.dist-info/top_level.txt
fastlimiter-0.1.0.dist-info/RECORD
