Metadata-Version: 2.1
Name: fastlimiter
Version: 0.1.0
Summary: A fast token bucket rate limiter
Home-page: https://github.com/anto18671/fastlimiter
Author: Anthony Therrien
License: MIT
Project-URL: Bug Tracker, https://github.com/anto18671/fastlimiter/issues
Project-URL: Source Code, https://github.com/anto18671/fastlimiter
Keywords: rate-limiter,token-bucket,fastapi,middleware
Classifier: Programming Language :: Python :: 3
Classifier: License :: OSI Approved :: MIT License
Classifier: Operating System :: OS Independent
Classifier: Development Status :: 3 - Alpha
Classifier: Intended Audience :: Developers
Classifier: Topic :: Software Development :: Libraries :: Python Modules
Requires-Python: >=3.8
License-File: LICENSE
Requires-Dist: fastapi >=0.65.0
Provides-Extra: dev
Requires-Dist: uvicorn >=0.30.6 ; extra == 'dev'
Requires-Dist: httpx >=0.27.2 ; extra == 'dev'
Requires-Dist: pytest >=8.3.3 ; extra == 'dev'
Requires-Dist: pytest-asyncio >=0.24.0 ; extra == 'dev'
